mangapy/__init__.py
mangapy/capabilities.py
mangapy/chapter_archiver.py
mangapy/cli.py
mangapy/download_manager.py
mangapy/fanfox.py
mangapy/mangadex.py
mangapy/mangarepository.py
mangapy/providers.py
mangapy/utils.py
mangapy-3.0.1.dist-info/licenses/LICENSE
mangapy-3.0.1.dist-info/METADATA
mangapy-3.0.1.dist-info/WHEEL
mangapy-3.0.1.dist-info/entry_points.txt
mangapy-3.0.1.dist-info/top_level.txt
mangapy-3.0.1.dist-info/RECORD
