Metadata-Version: 2.4
Name: mangapy
Version: 3.0.1
Summary: Manga downloader
Author-email: Alessandro Marzoli <alessandromarzoli@gmail.com>
License: MIT License
Project-URL: Homepage, https://github.com/alemar11/mangapy
Classifier: Development Status :: 5 - Production/Stable
Classifier: License :: OSI Approved :: MIT License
Classifier: Programming Language :: Python
Classifier: Programming Language :: Python :: 3.11
Classifier: Topic :: Games/Entertainment
Classifier: Topic :: Software Development :: Libraries :: Python Modules
Classifier: Intended Audience :: End Users/Desktop
Requires-Python: >=3.11
License-File: LICENSE
Requires-Dist: bs4
Requires-Dist: img2pdf
Requires-Dist: pillow
Requires-Dist: pyyaml
Requires-Dist: requests
Requires-Dist: tqdm
Dynamic: license-file
